weditorplus/__init__.py
weditorplus/__main__.py
weditorplus/static/favicon.ico
weditorplus/static/loading.svg
weditorplus/static/running.svg
weditorplus/static/style.css
weditorplus/static/ace/ace.js
weditorplus/static/ace/ext-language_tools.js
weditorplus/static/ace/keybinding-vim.js
weditorplus/static/ace/mode-python.js
weditorplus/static/ace/theme-monokai.js
weditorplus/static/cdn_libraries/cdn.jsdelivr.net/bootstrap/3.3.7/css/bootstrap.min.css
weditorplus/static/cdn_libraries/cdn.jsdelivr.net/bootstrap/3.3.7/css/bootstrap.min.css.map
weditorplus/static/cdn_libraries/cdn.jsdelivr.net/bootstrap/3.3.7/fonts/glyphicons-halflings-regular.woff2
weditorplus/static/cdn_libraries/cdn.jsdelivr.net/bootstrap/3.3.7/js/bootstrap.min.js
weditorplus/static/cdn_libraries/cdn.jsdelivr.net/bootstrap.select/1.12.2/css/bootstrap-select.min.css
weditorplus/static/cdn_libraries/cdn.jsdelivr.net/bootstrap.select/1.12.2/js/bootstrap-select.js.map
weditorplus/static/cdn_libraries/cdn.jsdelivr.net/bootstrap.select/1.12.2/js/bootstrap-select.min.js
weditorplus/static/cdn_libraries/cdn.jsdelivr.net/npm/vue-resource@1.5.1
weditorplus/static/cdn_libraries/cdn.jsdelivr.net/npm/ace-builds@1.4.12/src-noconflict/ace.min.js
weditorplus/static/cdn_libraries/cdn.jsdelivr.net/npm/ace-builds@1.4.12/src-noconflict/ext-language_tools.min.js
weditorplus/static/cdn_libraries/cdn.jsdelivr.net/npm/ace-builds@1.4.12/src-noconflict/ext-searchbox.min.js
weditorplus/static/cdn_libraries/cdn.jsdelivr.net/npm/ace-builds@1.4.12/src-noconflict/mode-python.min.js
weditorplus/static/cdn_libraries/cdn.jsdelivr.net/npm/ace-builds@1.4.12/src-noconflict/theme-monokai.js
weditorplus/static/cdn_libraries/cdn.jsdelivr.net/npm/jquery@3.3.1/dist/jquery.min.js
weditorplus/static/cdn_libraries/cdn.jsdelivr.net/npm/jstree@3.3.8/dist/jstree.min.js
weditorplus/static/cdn_libraries/cdn.jsdelivr.net/npm/jstree@3.3.8/dist/themes/default/32px.png
weditorplus-1.0.1.dist-info/METADATA
weditorplus-1.0.1.dist-info/WHEEL
weditorplus-1.0.1.dist-info/entry_points.txt
weditorplus-1.0.1.dist-info/top_level.txt
weditorplus-1.0.1.dist-info/RECORD
